purses3d/__init__.py
purses3d/hack.ttf
panda3d_purses3d-0.0.9.dist-info/LICENSE.txt
panda3d_purses3d-0.0.9.dist-info/METADATA
panda3d_purses3d-0.0.9.dist-info/WHEEL
panda3d_purses3d-0.0.9.dist-info/top_level.txt
panda3d_purses3d-0.0.9.dist-info/RECORD
