Metadata-Version: 2.1
Name: panda3d-purses3d
Version: 0.0.9
Summary: Ncurses-like text printing for Panda3D
Home-page: https://github.com/momojohobo/panda3d-purses3d
Author: momojohobo
Author-email: bandaibandai@rocketship.com
License: UNKNOWN
Platform: UNKNOWN
Classifier: Programming Language :: Python :: 3
Classifier: License :: OSI Approved :: MIT License
Classifier: Operating System :: OS Independent
Requires-Dist: panda3d
